Workbook

Sheet Formula & Legend
A1: Dhaka Ride-Fare Engine — Admin Cheat Sheet
A2: Enter values on the 'Rate Card (Enter These)' tab. This sheet explains what each column means and how the engine computes the final fare.
A4: FINAL FARE FORMULA
A5: final_fare = base_fare + (trip_rate x trip_distance_km) + (wait_rate x chargeable_wait_min) + pickup_fee
A7: PICKUP FEE FORMULA
A8: chargeable_km = MIN( MAX(0, reference_pickup_km - free_radius_km), cap_km )
A9: pickup_fee_raw = chargeable_km x pickup_rate
A10: pickup_fee = MIN( pickup_fee_raw, cap_pct x fare_before_pickup )
A11: pickup_rate = trip_rate x category_multiplier [multiplier is LOCKED per category, see table]
A13: LEGEND — what each term means
A14: Term | B14: Meaning
A15: final_fare | B15: Total amount the rider is charged for the completed trip.
A16: base_fare | B16: Fixed BDT amount per trip. Covers driver's fixed trip-initiation overhead (app interaction, locating rider) — NOT drive-to-pickup time, that's priced separately by pickup_fee.
A17: trip_rate | B17: BDT per km. Multiplied by the actual trip distance (loaded, rider onboard) to get the distance charge. This is the main lever — see Rate Card tab.
A18: trip_distance_km | B18: Actual road-network distance of the completed trip, rider onboard. Computed by the routing engine per trip, not entered by admin.
A19: wait_rate | B19: BDT per minute. Charged for waiting time beyond the free grace period.
A20: chargeable_wait_min | B20: Minutes the rider made the driver wait, minus the free_wait_min grace period. Computed by the engine per trip (wait_timer - free_wait_min, floored at 0).
A21: pickup_fee | B21: Charge for the driver's dead-mileage to reach the rider. See Pickup Fee Formula above.
A22: reference_pickup_km | B22: Road-network distance from driver's position (at accept) to the rider's pickup pin. Computed per trip by the routing engine, not entered by admin.
A23: free_radius_km | B23: Pickup distance (km) the rider is NOT charged for. Below this radius, pickup_fee = 0.
A24: cap_km | B24: Maximum chargeable pickup km — the rider is never billed for more than this many km of pickup, no matter how far the driver actually was.
A25: pickup_rate | B25: BDT per km, charged only on the chargeable portion of the pickup distance. Derived as trip_rate x category_multiplier — engine computes this, admin does not enter it directly.
... A29: free_wait_min | B29: Minutes of waiting the rider gets free before the wait_rate starts charging.
A31: NOTE
A32: Yellow cells on the Rate Card tab are the only values the admin should enter/edit. Everything else is either a fixed engine constant or computed per trip by the routing/dispatch engine — do not hardcode those into the admin panel.

Sheet Rate Card (Enter These)
A1: Enter yellow cells only. Grey cells are computed by formula — do not overwrite.
A2: Sub-Category | B2: trip_rate (BDT/km) | C2: category_ multiplier | D2: pickup_rate (BDT/km, computed) | E2: base_fare (BDT) | F2: wait_rate (BDT/min) | G2: free_wait_min | H2: free_radius_km | I2: cap_km | J2: cap_pct
A3: Bike Economy (100cc) | B3: 11.42 | C3: 0.75 | D3: =B3*C3 -> 8.565 | E3: 8 | F3: 1.33 | G3: 3 | H3: 1.2 | I3: 2 | J3: 0.4
A4: Bike Standard (125cc) | B4: 13.04 | C4: 0.75 | D4: =B4*C4 -> 9.78 | E4: 8.33 | F4: 1.5 | G4: 3 | H4: 1.2 | I4: 2 | J4: 0.4
A5: Bike Premium (150cc) | B5: 15.53 | C5: 0.75 | D5: =B5*C5 -> 11.6475 | E5: 8.33 | F5: 1.67 | G5: 3 | H5: 1.2 | I5: 2 | J5: 0.4
A6: CNG Standard (~200cc) | B6: 16.88 | C6: 0.8 | D6: =B6*C6 -> 13.504 | E6: 10.45 | F6: 1.82 | G6: 4 | H6: 1.8 | I6: 2 | J6: 0.4
A7: Car Economy (1000cc) | B7: 31.47 | C7: 0.9 | D7: =B7*C7 -> 28.323 | E7: 11.82 | F7: 2.27 | G7: 4 | H7: 1.8 | I7: 2 | J7: 0.4
A8: Car Standard (1500cc) | B8: 40.44 | C8: 0.9 | D8: =B8*C8 -> 36.396 | E8: 13.18 | F8: 2.73 | G8: 4 | H8: 2.8 | I8: 2 | J8: 0.4
A9: Car Premium (1500cc) | B9: 50.64 | C9: 0.9 | D9: =B9*C9 -> 45.576 | E9: 15 | F9: 3.33 | G9: 4 | H9: 2.8 | I9: 2 | J9: 0.4
A11: Yellow = admin enters. Grey (pickup_rate) = auto-computed, do not edit.
A12: category_multiplier is a locked pricing decision, not a cost figure — changing it re-prices deadhead compensation for that whole category.
A19: final_fare = base_fare + (trip_rate × 17) + (wait_rate × max(0, 5 − free_wait_min)) + 0 (no pickup km given) | C19: =B6*17 -> 286.96
C20: 8.7
A22: Final Fare | C22: KM | D22: Trip Rate | E22: Free Wait Time | F22: Actual Wait Time | G22: Actual Waiting Time | H22: Wait BDT/Min | I22: Chargable Wait Fee | M22: Ride | N22: Pathao | O22: uber
A23: Bike Economy (100cc) | B23: =E3 -> 8 | C23: =$C$20 -> 8.7 | D23: =B3 -> 11.42 | E23: =G3 -> 3 | F23: 5 | G23: =F23-E23 -> 2 | H23: =F3 -> 1.33 | I23: =MAX(0,G23)*H23 -> 2.66 | M23: =I23+D23*C23+B23 -> 110.014 | N23: 192 | O23: 125
A24: Bike Standard (125cc) | B24: =E4 -> 8.33 | C24: =$C$20 -> 8.7 | D24: =B4 -> 13.04 | E24: =G4 -> 3 | F24: 5 | G24: =F24-E24 -> 2 | H24: =F4 -> 1.5 | I24: =MAX(0,G24)*H24 -> 3 | M24: =I24+D24*C24+B24 -> 124.778 | N24: 192 | O24: 144
A25: Bike Premium (150cc) | B25: =E5 -> 8.33 | C25: =$C$20 -> 8.7 | D25: =B5 -> 15.53 | E25: =G5 -> 3 | F25: 5 | G25: =F25-E25 -> 2 | H25: =F5 -> 1.67 | I25: =MAX(0,G25)*H25 -> 3.34 | M25: =I25+D25*C25+B25 -> 146.781 | N25: 192
A26: CNG Standard (~200cc) | B26: =E6 -> 10.45 | C26: =$C$20 -> 8.7 | D26: =B6 -> 16.88 | E26: =G6 -> 4 | F26: 5 | G26: =F26-E26 -> 1 | H26: =F6 -> 1.82 | I26: =MAX(0,G26)*H26 -> 1.82 | M26: =I26+D26*C26+B26 -> 159.126 | N26: 314 | O26: 287
A27: Car Economy (1000cc) | B27: =E7 -> 11.82 | C27: =$C$20 -> 8.7 | D27: =B7 -> 31.47 | E27: =G7 -> 4 | F27: 5 | G27: =F27-E27 -> 1 | H27: =F7 -> 2.27 | I27: =MAX(0,G27)*H27 -> 2.27 | M27: =I27+D27*C27+B27 -> 287.879 | N27: 386 | O27: 522
A28: Car Standard (1500cc) | B28: =E8 -> 13.18 | C28: =$C$20 -> 8.7 | D28: =B8 -> 40.44 | E28: =G8 -> 4 | F28: 5 | G28: =F28-E28 -> 1 | H28: =F8 -> 2.73 | I28: =MAX(0,G28)*H28 -> 2.73 | M28: =I28+D28*C28+B28 -> 367.738 | O28: 448
A29: Car Premium (1500cc) | B29: =E9 -> 15 | C29: =$C$20 -> 8.7 | D29: =B9 -> 50.64 | E29: =G9 -> 4 | F29: 5 | G29: =F29-E29 -> 1 | H29: =F9 -> 3.33 | I29: =MAX(0,G29)*H29 -> 3.33 | M29: =I29+D29*C29+B29 -> 458.898 | N29: 530 | O29: 646
A30: Car XL | N30: 806 | O30: 716
A36: My Suggestions:
A37: Final rate | B37: Base Rate

Sheet Formula and Simulation
A1: final_fare = base_fare + (trip_rate × 17) + (wait_rate × max(0, 5 − free_wait_min)) + 0 (no pickup km given)
D6: 8.7
A8: Final Fare | B8: Base Rate | D8: KM | E8: Trip Rate | F8: Free Wait Time | G8: Actual Wait Time | H8: Actual Waiting Time | I8: Wait BDT/Min | J8: Chargable Wait Fee | N8: Ride | O8: Pathao | P8: uber
A9: Bike Economy (100cc) | B9: ='Rate Card (Enter These)'!E3 -> 8 | D9: =$D$6 -> 8.7 | E9: ='Rate Card (Enter These)'!B3 -> 11.42 | F9: ='Rate Card (Enter These)'!G3 -> 3 | G9: 5 | H9: =G9-F9 -> 2 | I9: ='Rate Card (Enter These)'!F3 -> 1.33 | J9: =MAX(0,H9)*I9 -> 2.66 | N9: =J9+E9*D9+B9 -> 110.014 | O9: 192 | P9: 125
A10: Bike Standard (125cc) | B10: ='Rate Card (Enter These)'!E4 -> 8.33 | D10: =$D$6 -> 8.7 | E10: ='Rate Card (Enter These)'!B4 -> 13.04 | F10: ='Rate Card (Enter These)'!G4 -> 3 | G10: 5 | H10: =G10-F10 -> 2 | I10: ='Rate Card (Enter These)'!F4 -> 1.5 | J10: =MAX(0,H10)*I10 -> 3 | N10: =J10+E10*D10+B10 -> 124.778 | O10: 192 | P10: 144
A11: Bike Premium (150cc) | B11: ='Rate Card (Enter These)'!E5 -> 8.33 | D11: =$D$6 -> 8.7 | E11: ='Rate Card (Enter These)'!B5 -> 15.53 | F11: ='Rate Card (Enter These)'!G5 -> 3 | G11: 5 | H11: =G11-F11 -> 2 | I11: ='Rate Card (Enter These)'!F5 -> 1.67 | J11: =MAX(0,H11)*I11 -> 3.34 | N11: =J11+E11*D11+B11 -> 146.781 | O11: 192
A12: CNG Standard (~200cc) | B12: ='Rate Card (Enter These)'!E6 -> 10.45 | D12: =$D$6 -> 8.7 | E12: ='Rate Card (Enter These)'!B6 -> 16.88 | F12: ='Rate Card (Enter These)'!G6 -> 4 | G12: 5 | H12: =G12-F12 -> 1 | I12: ='Rate Card (Enter These)'!F6 -> 1.82 | J12: =MAX(0,H12)*I12 -> 1.82 | N12: =J12+E12*D12+B12 -> 159.126 | O12: 314 | P12: 287
A13: Car Economy (1000cc) | B13: ='Rate Card (Enter These)'!E7 -> 11.82 | D13: =$D$6 -> 8.7 | E13: ='Rate Card (Enter These)'!B7 -> 31.47 | F13: ='Rate Card (Enter These)'!G7 -> 4 | G13: 5 | H13: =G13-F13 -> 1 | I13: ='Rate Card (Enter These)'!F7 -> 2.27 | J13: =MAX(0,H13)*I13 -> 2.27 | N13: =J13+E13*D13+B13 -> 287.879 | O13: 386 | P13: 522
A14: Car Standard (1500cc) | B14: ='Rate Card (Enter These)'!E8 -> 13.18 | D14: =$D$6 -> 8.7 | E14: ='Rate Card (Enter These)'!B8 -> 40.44 | F14: ='Rate Card (Enter These)'!G8 -> 4 | G14: 5 | H14: =G14-F14 -> 1 | I14: ='Rate Card (Enter These)'!F8 -> 2.73 | J14: =MAX(0,H14)*I14 -> 2.73 | N14: =J14+E14*D14+B14 -> 367.738 | P14: 448
A15: Car Premium (1500cc) | B15: ='Rate Card (Enter These)'!E9 -> 15 | D15: =$D$6 -> 8.7 | E15: ='Rate Card (Enter These)'!B9 -> 50.64 | F15: ='Rate Card (Enter These)'!G9 -> 4 | G15: 5 | H15: =G15-F15 -> 1 | I15: ='Rate Card (Enter These)'!F9 -> 3.33 | J15: =MAX(0,H15)*I15 -> 3.33 | N15: =J15+E15*D15+B15 -> 458.898 | O15: 530 | P15: 646
A16: Car XL | O16: 806 | P16: 716
A18: My Suggestions:
A19: Final rate | B19: Base KM | C19: X | D19: Cost BDT/KM
A23: FINAL FARE FORMULA
A24: final_fare = base_fare + (trip_rate x trip_distance_km) + (wait_rate x chargeable_wait_min) + pickup_fee
A26: PICKUP FEE FORMULA
A27: chargeable_km = MIN( MAX(0, reference_pickup_km - free_radius_km), cap_km )
A28: pickup_fee_raw = chargeable_km x pickup_rate
A29: pickup_fee = MIN( pickup_fee_raw, cap_pct x fare_before_pickup )
A30: pickup_rate = trip_rate x category_multiplier [multiplier is LOCKED per category, see table]
A33: Trip Rate = (Trip Bonus Rate + Fuel Cost BDT/KM + Trip Duration Cost + Maintenance Cost BDT/KM + Depreciation Cost BDT/KM + Parking Cost BDT/KM + Registration Renewal Cost BDT/KM + Cold Zone Surcharge BDT/Min) x Odd Hour Surcharge Multiplier
A34: Base Fare = Base KM x Trip Rate
A35: Total Fare = Max(Total KM, Base KM) x Trip Rate
A36: Waiting Time Rate = Waiting Fee BDT/Min x (Total Waiting Time - Free Waiting Time)
A37: Pickup Rate = Total Pickup distance KM x Trip Rate
... A59: Odd Hour Surcharge Multiplier
